Cvwriter/__init__.py
Cvwriter/video_writer.py
Cvwriter-0.0.3.dist-info/LICENSE
Cvwriter-0.0.3.dist-info/METADATA
Cvwriter-0.0.3.dist-info/WHEEL
Cvwriter-0.0.3.dist-info/top_level.txt
Cvwriter-0.0.3.dist-info/RECORD
