Metadata-Version: 2.1
Name: Cvwriter
Version: 0.0.3
Summary: The Video Writer Package is a Python library designed to simplify the process of capturing frames and saving them as video files. It provides an easy-to-use interface for creating video files from sequences of frames using the OpenCV library.
Author-email: Prince kumar <pk8840230@gmail.com>
Project-URL: Homepage, https://github.com/prince0310/Cvwriter
Project-URL: Bug Tracker, https://github.com/prince0310/Cvwriter/issues
Classifier: Programming Language :: Python :: 3
Classifier: Operating System :: OS Independent
Requires-Python: >=3.8
License-File: LICENSE
